magnus_extension_datastore_db/db.py
magnus_extension_datastore_db/integration.py
magnus_extension_datastore_db-0.1.1.dist-info/entry_points.txt
magnus_extension_datastore_db-0.1.1.dist-info/WHEEL
magnus_extension_datastore_db-0.1.1.dist-info/METADATA
magnus_extension_datastore_db-0.1.1.dist-info/RECORD
