Metadata-Version: 2.1
Name: magnus-extension-datastore-db
Version: 0.1.1
Summary: Magnus extension for DB as run log store
Home-page: https://github.com/AstraZeneca/magnus-extensions/
License: Apache-2.0
Author: Vijay Vammi
Author-email: vijay.vammi@astrazeneca.com
Requires-Python: >=3.6.1,<4.0.0
Classifier: License :: OSI Approved :: Apache Software License
Classifier: Programming Language :: Python :: 3
Classifier: Programming Language :: Python :: 3.10
Classifier: Programming Language :: Python :: 3.7
Classifier: Programming Language :: Python :: 3.8
Classifier: Programming Language :: Python :: 3.9
Requires-Dist: magnus
Requires-Dist: psycopg2-binary (>=2.9.3,<3.0.0)
Requires-Dist: sqlalchemy
Project-URL: Documentation, https://astrazeneca.github.io/magnus-extensions/
Project-URL: Repository, https://github.com/AstraZeneca/magnus-extensions/
